power_tools/__init__.py
power_tools/action_patterns.py
power_tools/admin.py
power_tools/docs.py
power_tools/helpers.py
power_tools/managers.py
power_tools/mixins.py
power_tools/cache/__init__.py
power_tools/cache/helpers.py
power_tools/cache/mixins.py
dj_drf_utils-1.5.3.dist-info/LICENSE.txt
dj_drf_utils-1.5.3.dist-info/METADATA
dj_drf_utils-1.5.3.dist-info/WHEEL
dj_drf_utils-1.5.3.dist-info/top_level.txt
dj_drf_utils-1.5.3.dist-info/RECORD
