Metadata-Version: 2.1
Name: dj-drf-utils
Version: 1.5.3
Summary: Useful functions and classes for Django and Django Rest Framework
Author-email: Cayo Rodrigues <cayo.rodrigues1914@gmail.com>
Maintainer-email: Cayo Rodrigues <cayo.rodrigues1914@gmail.com>
License: MIT License
Project-URL: repository, https://github.com/cayo-rodrigues/dj-drf-utils
Keywords: django,utils,serializers,generic,views,viewsets,mixins,email,login,model,manager,custom,action,shortcut,error,simple,rest,framework,dj,drf,admin,hash,password,user,filter,queryset,cache,management,by auth token,by user,group,key,docs,documentation,spectacular,customize,swagger,openapi
Classifier: Framework :: Django
Classifier: Programming Language :: Python :: 3
Requires-Python: >=3.8
License-File: LICENSE.txt
Requires-Dist: django-awesome-tools
